smsauth-0.1.0.dist-info/METADATA
smsauth-0.1.0.dist-info/RECORD
smsauth-0.1.0.dist-info/WHEEL
smsauth-0.1.0.dist-info/top_level.txt
smsauth3/__init__.py
smsauth3/main.py
