Metadata-Version: 2.1
Name: smsauth
Version: 0.1.0
Summary: Python API for SMS
Home-page: https://github.com/kwugfighter/sms-auth
Author: kwugfighter
Author-email: isaacli430@gmail.com
License: MIT
Keywords: auth,async,sms,twilio
Platform: UNKNOWN
Classifier: Development Status :: 3 - Alpha
Classifier: Intended Audience :: Developers
Classifier: Topic :: Software Development :: Build Tools
Classifier: License :: OSI Approved :: MIT License
Classifier: Programming Language :: Python :: 2.7
Classifier: Programming Language :: Python :: 3.6
Classifier: Programming Language :: Python :: 3.7
Requires-Dist: requests
Requires-Dist: aiohttp; python_version >= "3.6"
